sdh-scm-metrics
setup.cfg
setup.py
SDH_SCM_Metrics.egg-info/PKG-INFO
SDH_SCM_Metrics.egg-info/SOURCES.txt
SDH_SCM_Metrics.egg-info/dependency_links.txt
SDH_SCM_Metrics.egg-info/namespace_packages.txt
SDH_SCM_Metrics.egg-info/requires.txt
SDH_SCM_Metrics.egg-info/top_level.txt
sdh/__init__.py
sdh/metrics/__init__.py
sdh/metrics/scm/__init__.py
sdh/metrics/scm/api.py
sdh/metrics/scm/config.py
sdh/metrics/scm/store.py