Metadata-Version: 1.1
Name: SDH-SCM-Metrics
Version: 0.2.19
Summary: A service that calculates a small set of quantitative metrics on data from a GitLab SCM.
Home-page: https://github.com/smartdeveloperhub/sdh-scm-metrics
Author: Fernando Serena
Author-email: fernando.serena@centeropenmiddleware.com
License: Apache 2
Download-URL: https://github.com/smartdeveloperhub/sdh-scm-metrics/tarball/0.0.2
Keywords: linked-data,ontology,path,sdh,metrics
Platform: UNKNOWN
